{
  "a_comp_cor_00": {
    "CumulativeVarianceExplained": 0.0582791548,
    "Mask": "combined",
    "Method": "aCompCor",
    "Retained": true,
    "SingularValue": 106.8661928631,
    "VarianceExplained": 0.0582791548
  },
  "a_comp_cor_01": {
    "CumulativeVarianceExplained": 0.0919667964,
    "Mask": "combined",
    "Method": "aCompCor",
    "Retained": true,
    "SingularValue": 81.249186108,
    "VarianceExplained": 0.0336876416
  },
  "a_comp_cor_02": {
    "CumulativeVarianceExplained": 0.1241125143,
    "Mask": "combined",
    "Method": "aCompCor",
    "Retained": true,
    "SingularValue": 79.3679713693,
    "VarianceExplained": 0.0321457179
  },
  "a_comp_cor_03": {
    "CumulativeVarianceExplained": 0.152687019,
    "Mask": "combined",
    "Method": "aCompCor",
    "Retained": true,
    "SingularValue": 74.8295392264,
    "VarianceExplained": 0.0285745047
  },
  "a_comp_cor_04": {
    "CumulativeVarianceExplained": 0.1778089604,
    "Mask": "combined",
    "Method": "aCompCor",
    "Retained": true,
    "SingularValue": 70.1633496622,
    "VarianceExplained": 0.0251219414
  },
  "a_comp_cor_05": {
    "CumulativeVarianceExplained": 0.1986771101,
    "Mask": "combined",
    "Method": "aCompCor",
    "Retained": true,
    "SingularValue": 63.9478117158,
    "VarianceExplained": 0.0208681497
  },
  "a_comp_cor_06": {
    "CumulativeVarianceExplained": 0.2180056405,
    "Mask": "combined",
    "Method": "aCompCor",
    "Retained": true,
    "SingularValue": 61.5436333582,
    "VarianceExplained": 0.0193285303
  },
  "a_comp_cor_07": {
    "CumulativeVarianceExplained": 0.2363180702,
    "Mask": "combined",
    "Method": "aCompCor",
    "Retained": true,
    "SingularValue": 59.9041211564,
    "VarianceExplained": 0.0183124297
  },
  "a_comp_cor_08": {
    "CumulativeVarianceExplained": 0.2524468469,
    "Mask": "combined",
    "Method": "aCompCor",
    "Retained": true,
    "SingularValue": 56.2191701179,
    "VarianceExplained": 0.0161287767
  },
  "a_comp_cor_09": {
    "CumulativeVarianceExplained": 0.2680294912,
    "Mask": "combined",
    "Method": "aCompCor",
    "Retained": true,
    "SingularValue": 55.2591618981,
    "VarianceExplained": 0.0155826443
  },
  "a_comp_cor_10": {
    "CumulativeVarianceExplained": 0.282427179,
    "Mask": "combined",
    "Method": "aCompCor",
    "Retained": true,
    "SingularValue": 53.116578332,
    "VarianceExplained": 0.0143976878
  },
  "a_comp_cor_11": {
    "CumulativeVarianceExplained": 0.2965028654,
    "Mask": "combined",
    "Method": "aCompCor",
    "Retained": true,
    "SingularValue": 52.5192489121,
    "VarianceExplained": 0.0140756864
  },
  "a_comp_cor_12": {
    "CumulativeVarianceExplained": 0.3096191944,
    "Mask": "combined",
    "Method": "aCompCor",
    "Retained": true,
    "SingularValue": 50.6978878372,
    "VarianceExplained": 0.013116329
  },
  "a_comp_cor_13": {
    "CumulativeVarianceExplained": 0.3220508654,
    "Mask": "combined",
    "Method": "aCompCor",
    "Retained": true,
    "SingularValue": 49.3569676676,
    "VarianceExplained": 0.012431671
  },
  "a_comp_cor_14": {
    "CumulativeVarianceExplained": 0.3343599992,
    "Mask": "combined",
    "Method": "aCompCor",
    "Retained": true,
    "SingularValue": 49.1131129199,
    "VarianceExplained": 0.0123091338
  },
  "a_comp_cor_15": {
    "CumulativeVarianceExplained": 0.3463749922,
    "Mask": "combined",
    "Method": "aCompCor",
    "Retained": true,
    "SingularValue": 48.522757791,
    "VarianceExplained": 0.012014993
  },
  "a_comp_cor_16": {
    "CumulativeVarianceExplained": 0.3579304501,
    "Mask": "combined",
    "Method": "aCompCor",
    "Retained": true,
    "SingularValue": 47.5857912374,
    "VarianceExplained": 0.0115554579
  },
  "a_comp_cor_17": {
    "CumulativeVarianceExplained": 0.3692087825,
    "Mask": "combined",
    "Method": "aCompCor",
    "Retained": true,
    "SingularValue": 47.0117221626,
    "VarianceExplained": 0.0112783324
  },
  "a_comp_cor_18": {
    "CumulativeVarianceExplained": 0.3803845458,
    "Mask": "combined",
    "Method": "aCompCor",
    "Retained": true,
    "SingularValue": 46.797463335,
    "VarianceExplained": 0.0111757633
  },
  "a_comp_cor_19": {
    "CumulativeVarianceExplained": 0.3912733445,
    "Mask": "combined",
    "Method": "aCompCor",
    "Retained": true,
    "SingularValue": 46.1927375306,
    "VarianceExplained": 0.0108887987
  },
  "a_comp_cor_20": {
    "CumulativeVarianceExplained": 0.401765191,
    "Mask": "combined",
    "Method": "aCompCor",
    "Retained": true,
    "SingularValue": 45.3429403418,
    "VarianceExplained": 0.0104918465
  },
  "a_comp_cor_21": {
    "CumulativeVarianceExplained": 0.4121391464,
    "Mask": "combined",
    "Method": "aCompCor",
    "Retained": true,
    "SingularValue": 45.0874737731,
    "VarianceExplained": 0.0103739554
  },
  "a_comp_cor_22": {
    "CumulativeVarianceExplained": 0.422287664,
    "Mask": "combined",
    "Method": "aCompCor",
    "Retained": true,
    "SingularValue": 44.594882168,
    "VarianceExplained": 0.0101485176
  },
  "a_comp_cor_23": {
    "CumulativeVarianceExplained": 0.4321357848,
    "Mask": "combined",
    "Method": "aCompCor",
    "Retained": true,
    "SingularValue": 43.9299186129,
    "VarianceExplained": 0.0098481208
  },
  "a_comp_cor_24": {
    "CumulativeVarianceExplained": 0.4417326456,
    "Mask": "combined",
    "Method": "aCompCor",
    "Retained": true,
    "SingularValue": 43.365894938,
    "VarianceExplained": 0.0095968608
  },
  "a_comp_cor_25": {
    "CumulativeVarianceExplained": 0.4513002752,
    "Mask": "combined",
    "Method": "aCompCor",
    "Retained": true,
    "SingularValue": 43.2998000585,
    "VarianceExplained": 0.0095676295
  },
  "a_comp_cor_26": {
    "CumulativeVarianceExplained": 0.4606875725,
    "Mask": "combined",
    "Method": "aCompCor",
    "Retained": true,
    "SingularValue": 42.8897982322,
    "VarianceExplained": 0.0093872974
  },
  "a_comp_cor_27": {
    "CumulativeVarianceExplained": 0.4699153786,
    "Mask": "combined",
    "Method": "aCompCor",
    "Retained": true,
    "SingularValue": 42.5238859537,
    "VarianceExplained": 0.0092278061
  },
  "a_comp_cor_28": {
    "CumulativeVarianceExplained": 0.4790036866,
    "Mask": "combined",
    "Method": "aCompCor",
    "Retained": true,
    "SingularValue": 42.2012421944,
    "VarianceExplained": 0.009088308
  },
  "a_comp_cor_29": {
    "CumulativeVarianceExplained": 0.4880390327,
    "Mask": "combined",
    "Method": "aCompCor",
    "Retained": true,
    "SingularValue": 42.0780990102,
    "VarianceExplained": 0.0090353461
  },
  "a_comp_cor_30": {
    "CumulativeVarianceExplained": 0.4969792479,
    "Mask": "combined",
    "Method": "aCompCor",
    "Retained": true,
    "SingularValue": 41.8559979804,
    "VarianceExplained": 0.0089402152
  },
  "a_comp_cor_31": {
    "CumulativeVarianceExplained": 0.5057928034,
    "Mask": "combined",
    "Method": "aCompCor",
    "Retained": true,
    "SingularValue": 41.558444774,
    "VarianceExplained": 0.0088135555
  },
  "c_comp_cor_00": {
    "CumulativeVarianceExplained": 0.1001521946,
    "Mask": "CSF",
    "Method": "aCompCor",
    "Retained": true,
    "SingularValue": 52.6898361673,
    "VarianceExplained": 0.1001521946
  },
  "c_comp_cor_01": {
    "CumulativeVarianceExplained": 0.1829386798,
    "Mask": "CSF",
    "Method": "aCompCor",
    "Retained": true,
    "SingularValue": 47.9045025906,
    "VarianceExplained": 0.0827864852
  },
  "c_comp_cor_02": {
    "CumulativeVarianceExplained": 0.2565174454,
    "Mask": "CSF",
    "Method": "aCompCor",
    "Retained": true,
    "SingularValue": 45.1619683168,
    "VarianceExplained": 0.0735787656
  },
  "c_comp_cor_03": {
    "CumulativeVarianceExplained": 0.3251693728,
    "Mask": "CSF",
    "Method": "aCompCor",
    "Retained": true,
    "SingularValue": 43.6237484333,
    "VarianceExplained": 0.0686519274
  },
  "c_comp_cor_04": {
    "CumulativeVarianceExplained": 0.3773215507,
    "Mask": "CSF",
    "Method": "aCompCor",
    "Retained": true,
    "SingularValue": 38.0218144082,
    "VarianceExplained": 0.0521521779
  },
  "c_comp_cor_05": {
    "CumulativeVarianceExplained": 0.4215794046,
    "Mask": "CSF",
    "Method": "aCompCor",
    "Retained": true,
    "SingularValue": 35.0261004283,
    "VarianceExplained": 0.0442578539
  },
  "c_comp_cor_06": {
    "CumulativeVarianceExplained": 0.4544509177,
    "Mask": "CSF",
    "Method": "aCompCor",
    "Retained": true,
    "SingularValue": 30.1860620623,
    "VarianceExplained": 0.0328715131
  },
  "c_comp_cor_07": {
    "CumulativeVarianceExplained": 0.4840418471,
    "Mask": "CSF",
    "Method": "aCompCor",
    "Retained": true,
    "SingularValue": 28.6401914077,
    "VarianceExplained": 0.0295909294
  },
  "c_comp_cor_08": {
    "CumulativeVarianceExplained": 0.5099219646,
    "Mask": "CSF",
    "Method": "aCompCor",
    "Retained": true,
    "SingularValue": 26.7842651074,
    "VarianceExplained": 0.0258801175
  },
  "dropped_0": {
    "CumulativeVarianceExplained": 0.4235290802,
    "Mask": "Edge",
    "Method": "EdgeRegressor",
    "Retained": false,
    "SingularValue": 115.1398872405,
    "VarianceExplained": 0.0090067352
  },
  "dropped_1": {
    "CumulativeVarianceExplained": 0.4323267688,
    "Mask": "Edge",
    "Method": "EdgeRegressor",
    "Retained": false,
    "SingularValue": 113.7958421945,
    "VarianceExplained": 0.0087976885
  },
  "dropped_10": {
    "CumulativeVarianceExplained": 0.5058258553,
    "Mask": "Edge",
    "Method": "EdgeRegressor",
    "Retained": false,
    "SingularValue": 107.4501241863,
    "VarianceExplained": 0.0078438565
  },
  "dropped_11": {
    "CumulativeVarianceExplained": 0.5135993944,
    "Mask": "Edge",
    "Method": "EdgeRegressor",
    "Retained": false,
    "SingularValue": 106.9674135324,
    "VarianceExplained": 0.007773539
  },
  "dropped_12": {
    "CumulativeVarianceExplained": 0.5213236802,
    "Mask": "Edge",
    "Method": "EdgeRegressor",
    "Retained": false,
    "SingularValue": 106.6280018946,
    "VarianceExplained": 0.0077242858
  },
  "dropped_13": {
    "CumulativeVarianceExplained": 0.5289422121,
    "Mask": "Edge",
    "Method": "EdgeRegressor",
    "Retained": false,
    "SingularValue": 105.8955590047,
    "VarianceExplained": 0.0076185319
  },
  "dropped_14": {
    "CumulativeVarianceExplained": 0.5364994101,
    "Mask": "Edge",
    "Method": "EdgeRegressor",
    "Retained": false,
    "SingularValue": 105.4684360135,
    "VarianceExplained": 0.0075571981
  },
  "dropped_15": {
    "CumulativeVarianceExplained": 0.5440388457,
    "Mask": "Edge",
    "Method": "EdgeRegressor",
    "Retained": false,
    "SingularValue": 105.3444160333,
    "VarianceExplained": 0.0075394356
  },
  "dropped_16": {
    "CumulativeVarianceExplained": 0.5514692718,
    "Mask": "Edge",
    "Method": "EdgeRegressor",
    "Retained": false,
    "SingularValue": 104.5800785111,
    "VarianceExplained": 0.0074304261
  },
  "dropped_17": {
    "CumulativeVarianceExplained": 0.5588496646,
    "Mask": "Edge",
    "Method": "EdgeRegressor",
    "Retained": false,
    "SingularValue": 104.2273845128,
    "VarianceExplained": 0.0073803927
  },
  "dropped_18": {
    "CumulativeVarianceExplained": 0.5661735246,
    "Mask": "Edge",
    "Method": "EdgeRegressor",
    "Retained": false,
    "SingularValue": 103.8274342276,
    "VarianceExplained": 0.0073238601
  },
  "dropped_19": {
    "CumulativeVarianceExplained": 0.5734439427,
    "Mask": "Edge",
    "Method": "EdgeRegressor",
    "Retained": false,
    "SingularValue": 103.4479278362,
    "VarianceExplained": 0.0072704181
  },
  "dropped_2": {
    "CumulativeVarianceExplained": 0.4409828829,
    "Mask": "Edge",
    "Method": "EdgeRegressor",
    "Retained": false,
    "SingularValue": 112.8765146088,
    "VarianceExplained": 0.0086561142
  },
  "dropped_20": {
    "CumulativeVarianceExplained": 0.5806426353,
    "Mask": "Edge",
    "Method": "EdgeRegressor",
    "Retained": false,
    "SingularValue": 102.9363862482,
    "VarianceExplained": 0.0071986926
  },
  "dropped_21": {
    "CumulativeVarianceExplained": 0.5877542162,
    "Mask": "Edge",
    "Method": "EdgeRegressor",
    "Retained": false,
    "SingularValue": 102.3116715273,
    "VarianceExplained": 0.0071115809
  },
  "dropped_22": {
    "CumulativeVarianceExplained": 0.5948204025,
    "Mask": "Edge",
    "Method": "EdgeRegressor",
    "Retained": false,
    "SingularValue": 101.9846115957,
    "VarianceExplained": 0.0070661863
  },
  "dropped_23": {
    "CumulativeVarianceExplained": 0.6018616452,
    "Mask": "Edge",
    "Method": "EdgeRegressor",
    "Retained": false,
    "SingularValue": 101.8044496474,
    "VarianceExplained": 0.0070412427
  },
  "dropped_24": {
    "CumulativeVarianceExplained": 0.608837154,
    "Mask": "Edge",
    "Method": "EdgeRegressor",
    "Retained": false,
    "SingularValue": 101.3281344783,
    "VarianceExplained": 0.0069755087
  },
  "dropped_25": {
    "CumulativeVarianceExplained": 0.6157755424,
    "Mask": "Edge",
    "Method": "EdgeRegressor",
    "Retained": false,
    "SingularValue": 101.05816489,
    "VarianceExplained": 0.0069383884
  },
  "dropped_26": {
    "CumulativeVarianceExplained": 0.6226858733,
    "Mask": "Edge",
    "Method": "EdgeRegressor",
    "Retained": false,
    "SingularValue": 100.8536280517,
    "VarianceExplained": 0.0069103309
  },
  "dropped_27": {
    "CumulativeVarianceExplained": 0.6295525846,
    "Mask": "Edge",
    "Method": "EdgeRegressor",
    "Retained": false,
    "SingularValue": 100.5348180761,
    "VarianceExplained": 0.0068667113
  },
  "dropped_28": {
    "CumulativeVarianceExplained": 0.6363490189,
    "Mask": "Edge",
    "Method": "EdgeRegressor",
    "Retained": false,
    "SingularValue": 100.0190364572,
    "VarianceExplained": 0.0067964344
  },
  "dropped_29": {
    "CumulativeVarianceExplained": 0.6431213792,
    "Mask": "Edge",
    "Method": "EdgeRegressor",
    "Retained": false,
    "SingularValue": 99.8417375513,
    "VarianceExplained": 0.0067723603
  },
  "dropped_3": {
    "CumulativeVarianceExplained": 0.4494282601,
    "Mask": "Edge",
    "Method": "EdgeRegressor",
    "Retained": false,
    "SingularValue": 111.4940337144,
    "VarianceExplained": 0.0084453772
  },
  "dropped_30": {
    "CumulativeVarianceExplained": 0.6498816507,
    "Mask": "Edge",
    "Method": "EdgeRegressor",
    "Retained": false,
    "SingularValue": 99.752588115,
    "VarianceExplained": 0.0067602715
  },
  "dropped_31": {
    "CumulativeVarianceExplained": 0.6566111236,
    "Mask": "Edge",
    "Method": "EdgeRegressor",
    "Retained": false,
    "SingularValue": 99.5251006521,
    "VarianceExplained": 0.0067294728
  },
  "dropped_32": {
    "CumulativeVarianceExplained": 0.6633303457,
    "Mask": "Edge",
    "Method": "EdgeRegressor",
    "Retained": false,
    "SingularValue": 99.4492709149,
    "VarianceExplained": 0.0067192222
  },
  "dropped_33": {
    "CumulativeVarianceExplained": 0.6700075952,
    "Mask": "Edge",
    "Method": "EdgeRegressor",
    "Retained": false,
    "SingularValue": 99.1381714407,
    "VarianceExplained": 0.0066772495
  },
  "dropped_34": {
    "CumulativeVarianceExplained": 0.6766406705,
    "Mask": "Edge",
    "Method": "EdgeRegressor",
    "Retained": false,
    "SingularValue": 98.8096971408,
    "VarianceExplained": 0.0066330753
  },
  "dropped_35": {
    "CumulativeVarianceExplained": 0.6832519968,
    "Mask": "Edge",
    "Method": "EdgeRegressor",
    "Retained": false,
    "SingularValue": 98.6475712029,
    "VarianceExplained": 0.0066113262
  },
  "dropped_36": {
    "CumulativeVarianceExplained": 0.6898348844,
    "Mask": "Edge",
    "Method": "EdgeRegressor",
    "Retained": false,
    "SingularValue": 98.4351762858,
    "VarianceExplained": 0.0065828876
  },
  "dropped_37": {
    "CumulativeVarianceExplained": 0.6963951739,
    "Mask": "Edge",
    "Method": "EdgeRegressor",
    "Retained": false,
    "SingularValue": 98.2660744489,
    "VarianceExplained": 0.0065602895
  },
  "dropped_38": {
    "CumulativeVarianceExplained": 0.7029141886,
    "Mask": "Edge",
    "Method": "EdgeRegressor",
    "Retained": false,
    "SingularValue": 97.9564597859,
    "VarianceExplained": 0.0065190146
  },
  "dropped_39": {
    "CumulativeVarianceExplained": 0.7093663952,
    "Mask": "Edge",
    "Method": "EdgeRegressor",
    "Retained": false,
    "SingularValue": 97.4532294803,
    "VarianceExplained": 0.0064522066
  },
  "dropped_4": {
    "CumulativeVarianceExplained": 0.4578486018,
    "Mask": "Edge",
    "Method": "EdgeRegressor",
    "Retained": false,
    "SingularValue": 111.3286548635,
    "VarianceExplained": 0.0084203417
  },
  "dropped_40": {
    "CumulativeVarianceExplained": 0.7158117695,
    "Mask": "Edge",
    "Method": "EdgeRegressor",
    "Retained": false,
    "SingularValue": 97.4016191241,
    "VarianceExplained": 0.0064453743
  },
  "dropped_41": {
    "CumulativeVarianceExplained": 0.7222079262,
    "Mask": "Edge",
    "Method": "EdgeRegressor",
    "Retained": false,
    "SingularValue": 97.0290215399,
    "VarianceExplained": 0.0063961567
  },
  "dropped_42": {
    "CumulativeVarianceExplained": 0.7285766766,
    "Mask": "Edge",
    "Method": "EdgeRegressor",
    "Retained": false,
    "SingularValue": 96.8209227246,
    "VarianceExplained": 0.0063687504
  },
  "dropped_43": {
    "CumulativeVarianceExplained": 0.7349075626,
    "Mask": "Edge",
    "Method": "EdgeRegressor",
    "Retained": false,
    "SingularValue": 96.5326764421,
    "VarianceExplained": 0.0063308859
  },
  "dropped_44": {
    "CumulativeVarianceExplained": 0.7412362882,
    "Mask": "Edge",
    "Method": "EdgeRegressor",
    "Retained": false,
    "SingularValue": 96.5162047621,
    "VarianceExplained": 0.0063287256
  },
  "dropped_45": {
    "CumulativeVarianceExplained": 0.7475338646,
    "Mask": "Edge",
    "Method": "EdgeRegressor",
    "Retained": false,
    "SingularValue": 96.2783917905,
    "VarianceExplained": 0.0062975764
  },
  "dropped_46": {
    "CumulativeVarianceExplained": 0.7537820263,
    "Mask": "Edge",
    "Method": "EdgeRegressor",
    "Retained": false,
    "SingularValue": 95.8999174645,
    "VarianceExplained": 0.0062481617
  },
  "dropped_47": {
    "CumulativeVarianceExplained": 0.7599965186,
    "Mask": "Edge",
    "Method": "EdgeRegressor",
    "Retained": false,
    "SingularValue": 95.6411811233,
    "VarianceExplained": 0.0062144923
  },
  "dropped_48": {
    "CumulativeVarianceExplained": 0.7661992806,
    "Mask": "Edge",
    "Method": "EdgeRegressor",
    "Retained": false,
    "SingularValue": 95.5508733608,
    "VarianceExplained": 0.006202762
  },
  "dropped_49": {
    "CumulativeVarianceExplained": 0.7723769018,
    "Mask": "Edge",
    "Method": "EdgeRegressor",
    "Retained": false,
    "SingularValue": 95.35703533,
    "VarianceExplained": 0.0061776212
  },
  "dropped_5": {
    "CumulativeVarianceExplained": 0.4661073707,
    "Mask": "Edge",
    "Method": "EdgeRegressor",
    "Retained": false,
    "SingularValue": 110.2553721206,
    "VarianceExplained": 0.0082587689
  },
  "dropped_50": {
    "CumulativeVarianceExplained": 0.7785207342,
    "Mask": "Edge",
    "Method": "EdgeRegressor",
    "Retained": false,
    "SingularValue": 95.0958982633,
    "VarianceExplained": 0.0061438325
  },
  "dropped_51": {
    "CumulativeVarianceExplained": 0.7846278577,
    "Mask": "Edge",
    "Method": "EdgeRegressor",
    "Retained": false,
    "SingularValue": 94.8113767323,
    "VarianceExplained": 0.0061071235
  },
  "dropped_52": {
    "CumulativeVarianceExplained": 0.7907154067,
    "Mask": "Edge",
    "Method": "EdgeRegressor",
    "Retained": false,
    "SingularValue": 94.6593107799,
    "VarianceExplained": 0.006087549
  },
  "dropped_53": {
    "CumulativeVarianceExplained": 0.7967633143,
    "Mask": "Edge",
    "Method": "EdgeRegressor",
    "Retained": false,
    "SingularValue": 94.3506019926,
    "VarianceExplained": 0.0060479076
  },
  "dropped_54": {
    "CumulativeVarianceExplained": 0.802785294,
    "Mask": "Edge",
    "Method": "EdgeRegressor",
    "Retained": false,
    "SingularValue": 94.148140776,
    "VarianceExplained": 0.0060219797
  },
  "dropped_55": {
    "CumulativeVarianceExplained": 0.8087866974,
    "Mask": "Edge",
    "Method": "EdgeRegressor",
    "Retained": false,
    "SingularValue": 93.9871574629,
    "VarianceExplained": 0.0060014035
  },
  "dropped_56": {
    "CumulativeVarianceExplained": 0.8147503633,
    "Mask": "Edge",
    "Method": "EdgeRegressor",
    "Retained": false,
    "SingularValue": 93.691189989,
    "VarianceExplained": 0.0059636659
  },
  "dropped_57": {
    "CumulativeVarianceExplained": 0.8206971955,
    "Mask": "Edge",
    "Method": "EdgeRegressor",
    "Retained": false,
    "SingularValue": 93.5588646568,
    "VarianceExplained": 0.0059468321
  },
  "dropped_58": {
    "CumulativeVarianceExplained": 0.8266294062,
    "Mask": "Edge",
    "Method": "EdgeRegressor",
    "Retained": false,
    "SingularValue": 93.4437780219,
    "VarianceExplained": 0.0059322108
  },
  "dropped_59": {
    "CumulativeVarianceExplained": 0.8325349494,
    "Mask": "Edge",
    "Method": "EdgeRegressor",
    "Retained": false,
    "SingularValue": 93.233508715,
    "VarianceExplained": 0.0059055432
  },
  "dropped_6": {
    "CumulativeVarianceExplained": 0.4741452478,
    "Mask": "Edge",
    "Method": "EdgeRegressor",
    "Retained": false,
    "SingularValue": 108.7709159071,
    "VarianceExplained": 0.0080378772
  },
  "dropped_60": {
    "CumulativeVarianceExplained": 0.8384178272,
    "Mask": "Edge",
    "Method": "EdgeRegressor",
    "Retained": false,
    "SingularValue": 93.0544218761,
    "VarianceExplained": 0.0058828778
  },
  "dropped_61": {
    "CumulativeVarianceExplained": 0.8442911643,
    "Mask": "Edge",
    "Method": "EdgeRegressor",
    "Retained": false,
    "SingularValue": 92.9789352441,
    "VarianceExplained": 0.0058733371
  },
  "dropped_62": {
    "CumulativeVarianceExplained": 0.8501285386,
    "Mask": "Edge",
    "Method": "EdgeRegressor",
    "Retained": false,
    "SingularValue": 92.6938397949,
    "VarianceExplained": 0.0058373743
  },
  "dropped_63": {
    "CumulativeVarianceExplained": 0.8559248611,
    "Mask": "Edge",
    "Method": "EdgeRegressor",
    "Retained": false,
    "SingularValue": 92.3673268704,
    "VarianceExplained": 0.0057963225
  },
  "dropped_64": {
    "CumulativeVarianceExplained": 0.8617046918,
    "Mask": "Edge",
    "Method": "EdgeRegressor",
    "Retained": false,
    "SingularValue": 92.2358306494,
    "VarianceExplained": 0.0057798307
  },
  "dropped_65": {
    "CumulativeVarianceExplained": 0.8674605268,
    "Mask": "Edge",
    "Method": "EdgeRegressor",
    "Retained": false,
    "SingularValue": 92.0441662327,
    "VarianceExplained": 0.0057558349
  },
  "dropped_66": {
    "CumulativeVarianceExplained": 0.8732033046,
    "Mask": "Edge",
    "Method": "EdgeRegressor",
    "Retained": false,
    "SingularValue": 91.9397056657,
    "VarianceExplained": 0.0057427778
  },
  "dropped_67": {
    "CumulativeVarianceExplained": 0.8789021824,
    "Mask": "Edge",
    "Method": "EdgeRegressor",
    "Retained": false,
    "SingularValue": 91.5876204134,
    "VarianceExplained": 0.0056988778
  },
  "dropped_68": {
    "CumulativeVarianceExplained": 0.8845695017,
    "Mask": "Edge",
    "Method": "EdgeRegressor",
    "Retained": false,
    "SingularValue": 91.3336775471,
    "VarianceExplained": 0.0056673193
  },
  "dropped_69": {
    "CumulativeVarianceExplained": 0.8902241134,
    "Mask": "Edge",
    "Method": "EdgeRegressor",
    "Retained": false,
    "SingularValue": 91.2312233847,
    "VarianceExplained": 0.0056546117
  },
  "dropped_7": {
    "CumulativeVarianceExplained": 0.4821501075,
    "Mask": "Edge",
    "Method": "EdgeRegressor",
    "Retained": false,
    "SingularValue": 108.5472846956,
    "VarianceExplained": 0.0080048596
  },
  "dropped_70": {
    "CumulativeVarianceExplained": 0.8958389169,
    "Mask": "Edge",
    "Method": "EdgeRegressor",
    "Retained": false,
    "SingularValue": 90.9095237112,
    "VarianceExplained": 0.0056148035
  },
  "dropped_71": {
    "CumulativeVarianceExplained": 0.9014510521,
    "Mask": "Edge",
    "Method": "EdgeRegressor",
    "Retained": false,
    "SingularValue": 90.8879202103,
    "VarianceExplained": 0.0056121352
  },
  "dropped_72": {
    "CumulativeVarianceExplained": 0.9070381809,
    "Mask": "Edge",
    "Method": "EdgeRegressor",
    "Retained": false,
    "SingularValue": 90.6852067348,
    "VarianceExplained": 0.0055871289
  },
  "dropped_73": {
    "CumulativeVarianceExplained": 0.9125983618,
    "Mask": "Edge",
    "Method": "EdgeRegressor",
    "Retained": false,
    "SingularValue": 90.4662442828,
    "VarianceExplained": 0.0055601808
  },
  "dropped_74": {
    "CumulativeVarianceExplained": 0.9181311924,
    "Mask": "Edge",
    "Method": "EdgeRegressor",
    "Retained": false,
    "SingularValue": 90.2434709876,
    "VarianceExplained": 0.0055328306
  },
  "dropped_75": {
    "CumulativeVarianceExplained": 0.923646554,
    "Mask": "Edge",
    "Method": "EdgeRegressor",
    "Retained": false,
    "SingularValue": 90.1008937762,
    "VarianceExplained": 0.0055153616
  },
  "dropped_76": {
    "CumulativeVarianceExplained": 0.9291242627,
    "Mask": "Edge",
    "Method": "EdgeRegressor",
    "Retained": false,
    "SingularValue": 89.7928117856,
    "VarianceExplained": 0.0054777087
  },
  "dropped_77": {
    "CumulativeVarianceExplained": 0.9345826459,
    "Mask": "Edge",
    "Method": "EdgeRegressor",
    "Retained": false,
    "SingularValue": 89.6342757431,
    "VarianceExplained": 0.0054583832
  },
  "dropped_78": {
    "CumulativeVarianceExplained": 0.9400207415,
    "Mask": "Edge",
    "Method": "EdgeRegressor",
    "Retained": false,
    "SingularValue": 89.4675453047,
    "VarianceExplained": 0.0054380956
  },
  "dropped_79": {
    "CumulativeVarianceExplained": 0.9454231006,
    "Mask": "Edge",
    "Method": "EdgeRegressor",
    "Retained": false,
    "SingularValue": 89.1730925492,
    "VarianceExplained": 0.0054023591
  },
  "dropped_8": {
    "CumulativeVarianceExplained": 0.4900901244,
    "Mask": "Edge",
    "Method": "EdgeRegressor",
    "Retained": false,
    "SingularValue": 108.1067516406,
    "VarianceExplained": 0.007940017
  },
  "dropped_80": {
    "CumulativeVarianceExplained": 0.9508107648,
    "Mask": "Edge",
    "Method": "EdgeRegressor",
    "Retained": false,
    "SingularValue": 89.0517303056,
    "VarianceExplained": 0.0053876642
  },
  "dropped_81": {
    "CumulativeVarianceExplained": 0.9561687452,
    "Mask": "Edge",
    "Method": "EdgeRegressor",
    "Retained": false,
    "SingularValue": 88.8060721034,
    "VarianceExplained": 0.0053579804
  },
  "dropped_82": {
    "CumulativeVarianceExplained": 0.9614895612,
    "Mask": "Edge",
    "Method": "EdgeRegressor",
    "Retained": false,
    "SingularValue": 88.4975454993,
    "VarianceExplained": 0.005320816
  },
  "dropped_83": {
    "CumulativeVarianceExplained": 0.9667705331,
    "Mask": "Edge",
    "Method": "EdgeRegressor",
    "Retained": false,
    "SingularValue": 88.1655721804,
    "VarianceExplained": 0.0052809719
  },
  "dropped_84": {
    "CumulativeVarianceExplained": 0.9719854129,
    "Mask": "Edge",
    "Method": "EdgeRegressor",
    "Retained": false,
    "SingularValue": 87.6121334804,
    "VarianceExplained": 0.0052148798
  },
  "dropped_85": {
    "CumulativeVarianceExplained": 0.9771704089,
    "Mask": "Edge",
    "Method": "EdgeRegressor",
    "Retained": false,
    "SingularValue": 87.3607418556,
    "VarianceExplained": 0.0051849959
  },
  "dropped_86": {
    "CumulativeVarianceExplained": 0.9823214569,
    "Mask": "Edge",
    "Method": "EdgeRegressor",
    "Retained": false,
    "SingularValue": 87.0742824331,
    "VarianceExplained": 0.0051510481
  },
  "dropped_87": {
    "CumulativeVarianceExplained": 0.987425448,
    "Mask": "Edge",
    "Method": "EdgeRegressor",
    "Retained": false,
    "SingularValue": 86.6756395098,
    "VarianceExplained": 0.005103991
  },
  "dropped_88": {
    "CumulativeVarianceExplained": 0.9923997901,
    "Mask": "Edge",
    "Method": "EdgeRegressor",
    "Retained": false,
    "SingularValue": 85.5677140427,
    "VarianceExplained": 0.0049743421
  },
  "dropped_89": {
    "CumulativeVarianceExplained": 0.9966857286,
    "Mask": "Edge",
    "Method": "EdgeRegressor",
    "Retained": false,
    "SingularValue": 79.4264350141,
    "VarianceExplained": 0.0042859385
  },
  "dropped_9": {
    "CumulativeVarianceExplained": 0.4979819989,
    "Mask": "Edge",
    "Method": "EdgeRegressor",
    "Retained": false,
    "SingularValue": 107.7785129074,
    "VarianceExplained": 0.0078918745
  },
  "dropped_90": {
    "CumulativeVarianceExplained": 1.0,
    "Mask": "Edge",
    "Method": "EdgeRegressor",
    "Retained": false,
    "SingularValue": 69.8451312183,
    "VarianceExplained": 0.0033142714
  },
  "dropped_91": {
    "CumulativeVarianceExplained": 1.0,
    "Mask": "Edge",
    "Method": "EdgeRegressor",
    "Retained": false,
    "SingularValue": 0.0,
    "VarianceExplained": 0.0
  },
  "dropped_92": {
    "CumulativeVarianceExplained": 1.0,
    "Mask": "Edge",
    "Method": "EdgeRegressor",
    "Retained": false,
    "SingularValue": 0.0,
    "VarianceExplained": 0.0
  },
  "dropped_93": {
    "CumulativeVarianceExplained": 1.0,
    "Mask": "Edge",
    "Method": "EdgeRegressor",
    "Retained": false,
    "SingularValue": 0.0,
    "VarianceExplained": 0.0
  },
  "dropped_94": {
    "CumulativeVarianceExplained": 1.0,
    "Mask": "Edge",
    "Method": "EdgeRegressor",
    "Retained": false,
    "SingularValue": 0.0,
    "VarianceExplained": 0.0
  },
  "dropped_95": {
    "CumulativeVarianceExplained": 1.0,
    "Mask": "Edge",
    "Method": "EdgeRegressor",
    "Retained": false,
    "SingularValue": 0.0,
    "VarianceExplained": 0.0
  },
  "edge_comp_00": {
    "CumulativeVarianceExplained": 0.0418981511,
    "Mask": "Edge",
    "Method": "EdgeRegressor",
    "Retained": true,
    "SingularValue": 248.3359148733,
    "VarianceExplained": 0.0418981511
  },
  "edge_comp_01": {
    "CumulativeVarianceExplained": 0.0753049168,
    "Mask": "Edge",
    "Method": "EdgeRegressor",
    "Retained": true,
    "SingularValue": 221.7477994039,
    "VarianceExplained": 0.0334067657
  },
  "edge_comp_02": {
    "CumulativeVarianceExplained": 0.1050049427,
    "Mask": "Edge",
    "Method": "EdgeRegressor",
    "Retained": true,
    "SingularValue": 209.0838639542,
    "VarianceExplained": 0.0297000259
  },
  "edge_comp_03": {
    "CumulativeVarianceExplained": 0.1319768566,
    "Mask": "Edge",
    "Method": "EdgeRegressor",
    "Retained": true,
    "SingularValue": 199.2498417904,
    "VarianceExplained": 0.0269719139
  },
  "edge_comp_04": {
    "CumulativeVarianceExplained": 0.1573646252,
    "Mask": "Edge",
    "Method": "EdgeRegressor",
    "Retained": true,
    "SingularValue": 193.3100214005,
    "VarianceExplained": 0.0253877686
  },
  "edge_comp_05": {
    "CumulativeVarianceExplained": 0.1803139737,
    "Mask": "Edge",
    "Method": "EdgeRegressor",
    "Retained": true,
    "SingularValue": 183.7922877438,
    "VarianceExplained": 0.0229493485
  },
  "edge_comp_06": {
    "CumulativeVarianceExplained": 0.2008827032,
    "Mask": "Edge",
    "Method": "EdgeRegressor",
    "Retained": true,
    "SingularValue": 173.9986332343,
    "VarianceExplained": 0.0205687295
  },
  "edge_comp_07": {
    "CumulativeVarianceExplained": 0.2192076027,
    "Mask": "Edge",
    "Method": "EdgeRegressor",
    "Retained": true,
    "SingularValue": 164.233936966,
    "VarianceExplained": 0.0183248995
  },
  "edge_comp_08": {
    "CumulativeVarianceExplained": 0.2367520393,
    "Mask": "Edge",
    "Method": "EdgeRegressor",
    "Retained": true,
    "SingularValue": 160.6984972785,
    "VarianceExplained": 0.0175444365
  },
  "edge_comp_09": {
    "CumulativeVarianceExplained": 0.2530663737,
    "Mask": "Edge",
    "Method": "EdgeRegressor",
    "Retained": true,
    "SingularValue": 154.9625606496,
    "VarianceExplained": 0.0163143345
  },
  "edge_comp_10": {
    "CumulativeVarianceExplained": 0.2684852114,
    "Mask": "Edge",
    "Method": "EdgeRegressor",
    "Retained": true,
    "SingularValue": 150.6495787159,
    "VarianceExplained": 0.0154188377
  },
  "edge_comp_11": {
    "CumulativeVarianceExplained": 0.2829280376,
    "Mask": "Edge",
    "Method": "EdgeRegressor",
    "Retained": true,
    "SingularValue": 145.8035826989,
    "VarianceExplained": 0.0144428262
  },
  "edge_comp_12": {
    "CumulativeVarianceExplained": 0.2965808868,
    "Mask": "Edge",
    "Method": "EdgeRegressor",
    "Retained": true,
    "SingularValue": 141.7600146995,
    "VarianceExplained": 0.0136528492
  },
  "edge_comp_13": {
    "CumulativeVarianceExplained": 0.309294472,
    "Mask": "Edge",
    "Method": "EdgeRegressor",
    "Retained": true,
    "SingularValue": 136.7968580751,
    "VarianceExplained": 0.0127135852
  },
  "edge_comp_14": {
    "CumulativeVarianceExplained": 0.3216933875,
    "Mask": "Edge",
    "Method": "EdgeRegressor",
    "Retained": true,
    "SingularValue": 135.0933440701,
    "VarianceExplained": 0.0123989154
  },
  "edge_comp_15": {
    "CumulativeVarianceExplained": 0.3340394898,
    "Mask": "Edge",
    "Method": "EdgeRegressor",
    "Retained": true,
    "SingularValue": 134.8053223677,
    "VarianceExplained": 0.0123461023
  },
  "edge_comp_16": {
    "CumulativeVarianceExplained": 0.3453584264,
    "Mask": "Edge",
    "Method": "EdgeRegressor",
    "Retained": true,
    "SingularValue": 129.0758271008,
    "VarianceExplained": 0.0113189366
  },
  "edge_comp_17": {
    "CumulativeVarianceExplained": 0.3562066332,
    "Mask": "Edge",
    "Method": "EdgeRegressor",
    "Retained": true,
    "SingularValue": 126.3633353571,
    "VarianceExplained": 0.0108482068
  },
  "edge_comp_18": {
    "CumulativeVarianceExplained": 0.3667675567,
    "Mask": "Edge",
    "Method": "EdgeRegressor",
    "Retained": true,
    "SingularValue": 124.6789260052,
    "VarianceExplained": 0.0105609235
  },
  "edge_comp_19": {
    "CumulativeVarianceExplained": 0.3768416945,
    "Mask": "Edge",
    "Method": "EdgeRegressor",
    "Retained": true,
    "SingularValue": 121.7716094858,
    "VarianceExplained": 0.0100741378
  },
  "edge_comp_20": {
    "CumulativeVarianceExplained": 0.3865588196,
    "Mask": "Edge",
    "Method": "EdgeRegressor",
    "Retained": true,
    "SingularValue": 119.5944430553,
    "VarianceExplained": 0.0097171251
  },
  "edge_comp_21": {
    "CumulativeVarianceExplained": 0.3960387235,
    "Mask": "Edge",
    "Method": "EdgeRegressor",
    "Retained": true,
    "SingularValue": 118.1256117768,
    "VarianceExplained": 0.0094799039
  },
  "edge_comp_22": {
    "CumulativeVarianceExplained": 0.4053873213,
    "Mask": "Edge",
    "Method": "EdgeRegressor",
    "Retained": true,
    "SingularValue": 117.3046804878,
    "VarianceExplained": 0.0093485978
  },
  "edge_comp_23": {
    "CumulativeVarianceExplained": 0.4145223451,
    "Mask": "Edge",
    "Method": "EdgeRegressor",
    "Retained": true,
    "SingularValue": 115.9569927139,
    "VarianceExplained": 0.0091350238
  },
  "framewise_displacement": {
    "Units": "mm"
  },
  "rot_x": {
    "Description": "Rotation about left-right axis. Also known as \"pitch\".",
    "Units": "rad"
  },
  "rot_y": {
    "Description": "Rotation about anterior-posterior axis. Also known as \"roll\".",
    "Units": "rad"
  },
  "rot_z": {
    "Description": "Rotation about superior-inferior axis. Also known as \"yaw\".",
    "Units": "rad"
  },
  "t_comp_cor_00": {
    "CumulativeVarianceExplained": 0.1208407367,
    "Method": "tCompCor",
    "Retained": true,
    "SingularValue": 105.1174436657,
    "VarianceExplained": 0.1208407367
  },
  "t_comp_cor_01": {
    "CumulativeVarianceExplained": 0.2305950615,
    "Method": "tCompCor",
    "Retained": true,
    "SingularValue": 100.1795161864,
    "VarianceExplained": 0.1097543248
  },
  "t_comp_cor_02": {
    "CumulativeVarianceExplained": 0.321341852,
    "Method": "tCompCor",
    "Retained": true,
    "SingularValue": 91.0927358494,
    "VarianceExplained": 0.0907467905
  },
  "t_comp_cor_03": {
    "CumulativeVarianceExplained": 0.3818894551,
    "Method": "tCompCor",
    "Retained": true,
    "SingularValue": 74.4074782947,
    "VarianceExplained": 0.0605476031
  },
  "t_comp_cor_04": {
    "CumulativeVarianceExplained": 0.4305205281,
    "Method": "tCompCor",
    "Retained": true,
    "SingularValue": 66.6845207901,
    "VarianceExplained": 0.048631073
  },
  "t_comp_cor_05": {
    "CumulativeVarianceExplained": 0.4668202165,
    "Method": "tCompCor",
    "Retained": true,
    "SingularValue": 57.6128762257,
    "VarianceExplained": 0.0362996884
  },
  "t_comp_cor_06": {
    "CumulativeVarianceExplained": 0.5015582996,
    "Method": "tCompCor",
    "Retained": true,
    "SingularValue": 56.3600063547,
    "VarianceExplained": 0.0347380831
  },
  "trans_x": {
    "Description": "Translation along left-right axis.",
    "Units": "mm"
  },
  "trans_y": {
    "Description": "Translation along anterior-posterior axis.",
    "Units": "mm"
  },
  "trans_z": {
    "Description": "Translation along superior-inferior axis.",
    "Units": "mm"
  },
  "w_comp_cor_00": {
    "CumulativeVarianceExplained": 0.0451777368,
    "Mask": "WM",
    "Method": "aCompCor",
    "Retained": true,
    "SingularValue": 67.6031053529,
    "VarianceExplained": 0.0451777368
  },
  "w_comp_cor_01": {
    "CumulativeVarianceExplained": 0.0759198291,
    "Mask": "WM",
    "Method": "aCompCor",
    "Retained": true,
    "SingularValue": 55.7662089344,
    "VarianceExplained": 0.0307420923
  },
  "w_comp_cor_02": {
    "CumulativeVarianceExplained": 0.1028856842,
    "Mask": "WM",
    "Method": "aCompCor",
    "Retained": true,
    "SingularValue": 52.2289757259,
    "VarianceExplained": 0.0269658551
  },
  "w_comp_cor_03": {
    "CumulativeVarianceExplained": 0.1266804883,
    "Mask": "WM",
    "Method": "aCompCor",
    "Retained": true,
    "SingularValue": 49.0620258179,
    "VarianceExplained": 0.023794804
  },
  "w_comp_cor_04": {
    "CumulativeVarianceExplained": 0.1460159367,
    "Mask": "WM",
    "Method": "aCompCor",
    "Retained": true,
    "SingularValue": 44.2263943423,
    "VarianceExplained": 0.0193354484
  },
  "w_comp_cor_05": {
    "CumulativeVarianceExplained": 0.1646440922,
    "Mask": "WM",
    "Method": "aCompCor",
    "Retained": true,
    "SingularValue": 43.4099552326,
    "VarianceExplained": 0.0186281555
  },
  "w_comp_cor_06": {
    "CumulativeVarianceExplained": 0.1818000285,
    "Mask": "WM",
    "Method": "aCompCor",
    "Retained": true,
    "SingularValue": 41.6592668883,
    "VarianceExplained": 0.0171559363
  },
  "w_comp_cor_07": {
    "CumulativeVarianceExplained": 0.1968235648,
    "Mask": "WM",
    "Method": "aCompCor",
    "Retained": true,
    "SingularValue": 38.9843678397,
    "VarianceExplained": 0.0150235363
  },
  "w_comp_cor_08": {
    "CumulativeVarianceExplained": 0.2116266898,
    "Mask": "WM",
    "Method": "aCompCor",
    "Retained": true,
    "SingularValue": 38.6973400429,
    "VarianceExplained": 0.014803125
  },
  "w_comp_cor_09": {
    "CumulativeVarianceExplained": 0.2259710184,
    "Mask": "WM",
    "Method": "aCompCor",
    "Retained": true,
    "SingularValue": 38.0929426576,
    "VarianceExplained": 0.0143443286
  },
  "w_comp_cor_10": {
    "CumulativeVarianceExplained": 0.2401934646,
    "Mask": "WM",
    "Method": "aCompCor",
    "Retained": true,
    "SingularValue": 37.9307613786,
    "VarianceExplained": 0.0142224462
  },
  "w_comp_cor_11": {
    "CumulativeVarianceExplained": 0.2539381461,
    "Mask": "WM",
    "Method": "aCompCor",
    "Retained": true,
    "SingularValue": 37.2882284049,
    "VarianceExplained": 0.0137446815
  },
  "w_comp_cor_12": {
    "CumulativeVarianceExplained": 0.2673329947,
    "Mask": "WM",
    "Method": "aCompCor",
    "Retained": true,
    "SingularValue": 36.8106354275,
    "VarianceExplained": 0.0133948486
  },
  "w_comp_cor_13": {
    "CumulativeVarianceExplained": 0.2805998934,
    "Mask": "WM",
    "Method": "aCompCor",
    "Retained": true,
    "SingularValue": 36.6344028455,
    "VarianceExplained": 0.0132668987
  },
  "w_comp_cor_14": {
    "CumulativeVarianceExplained": 0.2934468177,
    "Mask": "WM",
    "Method": "aCompCor",
    "Retained": true,
    "SingularValue": 36.0498940755,
    "VarianceExplained": 0.0128469243
  },
  "w_comp_cor_15": {
    "CumulativeVarianceExplained": 0.3060248662,
    "Mask": "WM",
    "Method": "aCompCor",
    "Retained": true,
    "SingularValue": 35.6706516725,
    "VarianceExplained": 0.0125780485
  },
  "w_comp_cor_16": {
    "CumulativeVarianceExplained": 0.3183619965,
    "Mask": "WM",
    "Method": "aCompCor",
    "Retained": true,
    "SingularValue": 35.3273846073,
    "VarianceExplained": 0.0123371303
  },
  "w_comp_cor_17": {
    "CumulativeVarianceExplained": 0.3305227237,
    "Mask": "WM",
    "Method": "aCompCor",
    "Retained": true,
    "SingularValue": 35.0739100114,
    "VarianceExplained": 0.0121607272
  },
  "w_comp_cor_18": {
    "CumulativeVarianceExplained": 0.3424722303,
    "Mask": "WM",
    "Method": "aCompCor",
    "Retained": true,
    "SingularValue": 34.7679749466,
    "VarianceExplained": 0.0119495065
  },
  "w_comp_cor_19": {
    "CumulativeVarianceExplained": 0.3543092823,
    "Mask": "WM",
    "Method": "aCompCor",
    "Retained": true,
    "SingularValue": 34.6039908972,
    "VarianceExplained": 0.0118370521
  },
  "w_comp_cor_20": {
    "CumulativeVarianceExplained": 0.3658471875,
    "Mask": "WM",
    "Method": "aCompCor",
    "Retained": true,
    "SingularValue": 34.1639354853,
    "VarianceExplained": 0.0115379052
  },
  "w_comp_cor_21": {
    "CumulativeVarianceExplained": 0.3772822478,
    "Mask": "WM",
    "Method": "aCompCor",
    "Retained": true,
    "SingularValue": 34.0113318796,
    "VarianceExplained": 0.0114350603
  },
  "w_comp_cor_22": {
    "CumulativeVarianceExplained": 0.3885576707,
    "Mask": "WM",
    "Method": "aCompCor",
    "Retained": true,
    "SingularValue": 33.7730926405,
    "VarianceExplained": 0.011275423
  },
  "w_comp_cor_23": {
    "CumulativeVarianceExplained": 0.3996939306,
    "Mask": "WM",
    "Method": "aCompCor",
    "Retained": true,
    "SingularValue": 33.564029117,
    "VarianceExplained": 0.0111362599
  },
  "w_comp_cor_24": {
    "CumulativeVarianceExplained": 0.4107212951,
    "Mask": "WM",
    "Method": "aCompCor",
    "Retained": true,
    "SingularValue": 33.3995237137,
    "VarianceExplained": 0.0110273644
  },
  "w_comp_cor_25": {
    "CumulativeVarianceExplained": 0.4215801852,
    "Mask": "WM",
    "Method": "aCompCor",
    "Retained": true,
    "SingularValue": 33.1434055258,
    "VarianceExplained": 0.0108588902
  },
  "w_comp_cor_26": {
    "CumulativeVarianceExplained": 0.4322906705,
    "Mask": "WM",
    "Method": "aCompCor",
    "Retained": true,
    "SingularValue": 32.9161463968,
    "VarianceExplained": 0.0107104853
  },
  "w_comp_cor_27": {
    "CumulativeVarianceExplained": 0.4429023725,
    "Mask": "WM",
    "Method": "aCompCor",
    "Retained": true,
    "SingularValue": 32.764001153,
    "VarianceExplained": 0.010611702
  },
  "w_comp_cor_28": {
    "CumulativeVarianceExplained": 0.4533368074,
    "Mask": "WM",
    "Method": "aCompCor",
    "Retained": true,
    "SingularValue": 32.4891895347,
    "VarianceExplained": 0.0104344349
  },
  "w_comp_cor_29": {
    "CumulativeVarianceExplained": 0.4637065624,
    "Mask": "WM",
    "Method": "aCompCor",
    "Retained": true,
    "SingularValue": 32.388337587,
    "VarianceExplained": 0.010369755
  },
  "w_comp_cor_30": {
    "CumulativeVarianceExplained": 0.4738555681,
    "Mask": "WM",
    "Method": "aCompCor",
    "Retained": true,
    "SingularValue": 32.0417448936,
    "VarianceExplained": 0.0101490057
  },
  "w_comp_cor_31": {
    "CumulativeVarianceExplained": 0.4839702621,
    "Mask": "WM",
    "Method": "aCompCor",
    "Retained": true,
    "SingularValue": 31.9875358667,
    "VarianceExplained": 0.0101146941
  },
  "w_comp_cor_32": {
    "CumulativeVarianceExplained": 0.4938963106,
    "Mask": "WM",
    "Method": "aCompCor",
    "Retained": true,
    "SingularValue": 31.6878378394,
    "VarianceExplained": 0.0099260485
  },
  "w_comp_cor_33": {
    "CumulativeVarianceExplained": 0.5038067606,
    "Mask": "WM",
    "Method": "aCompCor",
    "Retained": true,
    "SingularValue": 31.6629296752,
    "VarianceExplained": 0.0099104499
  }
}